setup.py
news_ex_forex_next3/__init__.py
news_ex_forex_next3/news_ex_forex_next3.py
news_ex_forex_next3.egg-info/PKG-INFO
news_ex_forex_next3.egg-info/SOURCES.txt
news_ex_forex_next3.egg-info/dependency_links.txt
news_ex_forex_next3.egg-info/not-zip-safe
news_ex_forex_next3.egg-info/top_level.txt