Metadata-Version: 1.0
Name: news-ex-forex-next3
Version: 1.40
Summary: news_ex_forex_next3
Home-page: UNKNOWN
Author: omid
Author-email: UNKNOWN
License: UNKNOWN
Platform: UNKNOWN
